espresso_config/__init__.py
espresso_config/builtin_refs.py
espresso_config/command_line.py
espresso_config/exceptions.py
espresso_config/experimental.py
espresso_config/functional.py
espresso_config/instantiate.py
espresso_config/logging.py
espresso_config/meta_params.py
espresso_config/node.py
espresso_config/parser.py
espresso_config/registry.py
espresso_config/utils.py
espresso_config-0.11.1.dist-info/LICENSE
espresso_config-0.11.1.dist-info/METADATA
espresso_config-0.11.1.dist-info/WHEEL
espresso_config-0.11.1.dist-info/top_level.txt
espresso_config-0.11.1.dist-info/RECORD
