Metadata-Version: 2.1
Name: espresso-config
Version: 0.11.1
Summary: A struct config parser that you can set up in the
Home-page: https://github.com/soldni/espresso-config
Author: Luca Soldaini
Author-email: luca@soldaini.net
Project-URL: Bug Tracker, https://github.com/soldni/espresso-config/issues
Classifier: Programming Language :: Python :: 3
Classifier: License :: OSI Approved :: MIT License
Classifier: Operating System :: OS Independent
Requires-Python: >=3.8
License-File: LICENSE
Requires-Dist: pyyaml (>=6)
